[[{"__type__":"cc.Prefab","_name":"Runner","data":{"__id__":1},"asyncLoadAssets":false},{"__type__":"cc.Node","_name":"Runner","_children":[{"__id__":2}],"_components":[{"__type__":"cc.Sprite","node":{"__id__":1},"_spriteFrame":{"__uuid__":"a1gD3Bo61FKI6T/6GDgddv"}},{"__type__":"cc.BoxCollider","node":{"__id__":1},"_size":{"__type__":"cc.Size","width":198,"height":188}},{"__type__":"50ccdV7AX5OirJJ3F55d28/","node":{"__id__":1},"laser":{"__id__":2}}],"_prefab":{"__type__":"cc.PrefabInfo","root":{"__id__":1},"asset":{"__uuid__":"8dO3ay96ZPiZ2S2L1nDePu"},"fileId":"ffx3O3+xxE65oXnV93A1rP"},"_contentSize":{"__type__":"cc.Size","width":198,"height":188},"_scaleX":0.25,"_scaleY":0.25,"_position":{"__type__":"cc.Vec2","x":569,"y":292},"groupIndex":3},{"__type__":"cc.Node","_name":"RunnerLaser","_parent":{"__id__":1},"_active":false,"_components":[{"__type__":"cc.Sprite","node":{"__id__":2},"_spriteFrame":{"__uuid__":"a8fR/NuD1LOYQbEuHfCGJ2"}},{"__type__":"cc.BoxCollider","node":{"__id__":2},"_size":{"__type__":"cc.Size","width":9,"height":54}},{"__type__":"26bebxAzGBOVLvRkJxm7ntR","node":{"__id__":2}}],"_prefab":{"__type__":"cc.PrefabInfo","root":{"__id__":1},"asset":{"__uuid__":"8dO3ay96ZPiZ2S2L1nDePu"},"fileId":"3dUlmnowJNn6ByA8dy0XBn"},"_contentSize":{"__type__":"cc.Size","width":9,"height":54},"_position":{"__type__":"cc.Vec2","y":-135},"groupIndex":4}],{"__type__":"cc.SpriteFrame","content":{"name":"spaceShips_001","texture":"04WHbskHBJ/aL1eHscGavP","rect":[0,0,198,188],"offset":[0,0],"originalSize":[198,188]}},{"__type__":"cc.SpriteFrame","content":{"name":"laserRed01","texture":"12mpcVSH1DE48xQCCm+yYq","rect":[0,0,9,54],"offset":[0,0],"originalSize":[9,54]}}]